<?xml version="1.0" encoding="UTF-8"?>
<EmployeeDetail>
	<Employee>
		<Emp-id>1</Emp-id>
		<Emp-name>Tenzin</Emp-name>
		<Emp-age>50</Emp-age>
		<Emp-salary>76000</Emp-salary>
		<Emp-emailid>tenzin@gmail.com</Emp-emailid>
		<Emp-phonenum>7018769320</Emp-phonenum>
		<Emp-designation>Programmer</Emp-designation>
	</Employee>
	<Employee>
		<Emp-id>2</Emp-id>
		<Emp-name>David</Emp-name>
		<Emp-age>42</Emp-age>
		<Emp-salary>65000</Emp-salary>
		<Emp-emailid>David@gmail.com</Emp-emailid>
		<Emp-phonenum>9898769320</Emp-phonenum>
		<Emp-designation>Marketer</Emp-designation>
	</Employee>
	<Employee>
		<Emp-id>3</Emp-id>
		<Emp-name>Johan</Emp-name>
		<Emp-age>46</Emp-age>
		<Emp-salary>150000</Emp-salary>
		<Emp-emailid>jonah@gmail.com</Emp-emailid>
		<Emp-phonenum>8374993848</Emp-phonenum>
		<Emp-designation>Accountant</Emp-designation>
	</Employee>
	<Employee>
		<Emp-id>4</Emp-id>
		<Emp-name>Natalie</Emp-name>
		<Emp-age>24</Emp-age>
		<Emp-salary>90000</Emp-salary>
		<Emp-emailid>natalie@gmail.com</Emp-emailid>
		<Emp-phonenum>9873647363</Emp-phonenum>
		<Emp-designation>Model</Emp-designation>
	</Employee>
	<Employee>
		<Emp-id>5</Emp-id>
		<Emp-name>Todd</Emp-name>
		<Emp-age>27</Emp-age>
		<Emp-salary>80000</Emp-salary>
		<Emp-emailid>todderic@gmail.com</Emp-emailid>
		<Emp-phonenum>9247362843</Emp-phonenum>
		<Emp-designation>Influencer</Emp-designation>
	</Employee>
	<Employee>
		<Emp-id>6</Emp-id>
		<Emp-name>Ilya</Emp-name>
		<Emp-age>29</Emp-age>
		<Emp-salary>57000</Emp-salary>
		<Emp-emailid>ilya@gmail.com</Emp-emailid>
		<Emp-phonenum>7634638363</Emp-phonenum>
		<Emp-designation>Producer</Emp-designation>
	</Employee>
	<Employee>
		<Emp-id>7</Emp-id>
		<Emp-name>Robert</Emp-name>
		<Emp-age>42</Emp-age>
		<Emp-salary>66000</Emp-salary>
		<Emp-emailid>robert@gmail.com</Emp-emailid>
		<Emp-phonenum>92637283474</Emp-phonenum>
		<Emp-designation>Developer</Emp-designation>
	</Employee>
	<Employee>
		<Emp-id>8</Emp-id>
		<Emp-name>Mundane</Emp-name>
		<Emp-age>27</Emp-age>
		<Emp-salary>175000</Emp-salary>
		<Emp-emailid>mundane@gmail.com</Emp-emailid>
		<Emp-phonenum>736476364</Emp-phonenum>
		<Emp-designation>Manager</Emp-designation>
	</Employee>
</EmployeeDetail>